dtocean_installation/__init__.py
dtocean_installation-2.0.1.dist-info/METADATA
dtocean_installation-2.0.1.dist-info/WHEEL
dtocean_installation-2.0.1.dist-info/RECORD
